hdl/memory/colour_bram.sv
// colour_bram.sv
// Dual-port colour storage for one 256x256 sixteenth.
// 6-bit colour padded to 8 bits, tile-ordered addressing.
//
// Port A (read only)  — controller, dedicated, zero stall
// Port B (contested)  — controller write takes priority over b2d read
//                       b2d_rd_grant asserted when b2d read is served

module colour_bram (
    input  logic        clk,

    input  logic [8:0]  ctrl_rd_x,
    input  logic [8:0]  ctrl_rd_y,
    input  logic        ctrl_rd_en,
    output logic [7:0]  ctrl_rd_data,

    input  logic [8:0]  ctrl_wr_x,
    input  logic [8:0]  ctrl_wr_y,
    input  logic        ctrl_wr_en,
    input  logic [7:0]  ctrl_wr_data,

    input  logic [12:0] b2d_word_addr,
    input  logic        b2d_rd_en,
    output logic        b2d_rd_grant,
    output logic [63:0] b2d_rd_data
);

    (* ram_style = "block" *)
    logic [63:0] mem [0:8191];

    function [12:0] word_addr(input logic [8:0] x, input logic [8:0] y);
        logic [15:0] ta;
        ta = {y[7:4], x[7:4], y[3:0], x[3:0]};
        return ta[15:3];
    endfunction

    function [2:0] byte_off(input logic [8:0] x, input logic [8:0] y);
        logic [15:0] ta;
        ta = {y[7:4], x[7:4], y[3:0], x[3:0]};
        return ta[2:0];
    endfunction

    // Port A — controller dedicated read
    logic [63:0] a_rd_word;
    logic [2:0]  a_byte_off_reg;

    always_ff @(posedge clk) begin
        if (ctrl_rd_en) begin
            a_rd_word      <= mem[word_addr(ctrl_rd_x, ctrl_rd_y)];
            a_byte_off_reg <= byte_off(ctrl_rd_x, ctrl_rd_y);
        end
    end

    always_comb begin
        case (a_byte_off_reg)
            3'd0: ctrl_rd_data = a_rd_word[7:0];
            3'd1: ctrl_rd_data = a_rd_word[15:8];
            3'd2: ctrl_rd_data = a_rd_word[23:16];
            3'd3: ctrl_rd_data = a_rd_word[31:24];
            3'd4: ctrl_rd_data = a_rd_word[39:32];
            3'd5: ctrl_rd_data = a_rd_word[47:40];
            3'd6: ctrl_rd_data = a_rd_word[55:48];
            default: ctrl_rd_data = a_rd_word[63:56];
        endcase
    end

    // Port B arbitration
    assign b2d_rd_grant = b2d_rd_en && !ctrl_wr_en;

    // Read-modify-write for controller write
    logic [63:0] b_wr_word;
    logic [2:0]  wr_byte_off;
    assign wr_byte_off = byte_off(ctrl_wr_x, ctrl_wr_y);

    always_comb begin
        b_wr_word = mem[word_addr(ctrl_wr_x, ctrl_wr_y)];
        case (wr_byte_off)
            3'd0: b_wr_word[7:0]   = ctrl_wr_data;
            3'd1: b_wr_word[15:8]  = ctrl_wr_data;
            3'd2: b_wr_word[23:16] = ctrl_wr_data;
            3'd3: b_wr_word[31:24] = ctrl_wr_data;
            3'd4: b_wr_word[39:32] = ctrl_wr_data;
            3'd5: b_wr_word[47:40] = ctrl_wr_data;
            3'd6: b_wr_word[55:48] = ctrl_wr_data;
            default: b_wr_word[63:56] = ctrl_wr_data;
        endcase
    end

    always_ff @(posedge clk) begin
        if (ctrl_wr_en)
            mem[word_addr(ctrl_wr_x, ctrl_wr_y)] <= b_wr_word;
        else if (b2d_rd_en)
            b2d_rd_data <= mem[b2d_word_addr];
    end

endmodule

tb/memory/tb_colour_bram.sv
`timescale 1ns/1ps

module tb_colour_bram;

    int tests_run = 0, tests_passed = 0, tests_failed = 0;
    string current_suite = "";

    task automatic suite(input string name);
        current_suite = name;
        $display("\n%0s", {72{"="}});
        $display("  SUITE: %s", name);
        $display("%0s", {72{"="}});
    endtask

    task automatic check(input logic cond, input string desc);
        tests_run++;
        if (cond) begin tests_passed++; $display("  [PASS] %s", desc); end
        else       begin tests_failed++; $display("  [FAIL] %s  (suite: %s)", desc, current_suite); end
    endtask

    task automatic summary();
        $display("\n%0s", {72{"="}});
        $display("  RESULTS: %0d / %0d passed", tests_passed, tests_run);
        if (tests_failed == 0) $display("  ALL TESTS PASSED");
        else $display("  %0d TEST(S) FAILED", tests_failed);
        $display("%0s\n", {72{"="}});
    endtask

    logic        clk = 0;
    always #5 clk = ~clk;
    task automatic tick(input int n = 1); repeat(n) @(posedge clk); #1; endtask

    logic [8:0]  a_x, a_y;
    logic        a_rd, a_we;
    logic [7:0]  a_wdata, a_rdata;
    logic [12:0] b_word_addr;
    logic        b_rd, b_rd_grant;
    logic [63:0] b_rdata;
    logic        ctrl_wr_en;
    logic [8:0]  ctrl_wr_x, ctrl_wr_y;
    logic [7:0]  ctrl_wr_data;

    colour_bram dut (
        .clk           (clk),
        .ctrl_rd_x     (a_x),
        .ctrl_rd_y     (a_y),
        .ctrl_rd_en    (a_rd),
        .ctrl_rd_data  (a_rdata),
        .ctrl_wr_x     (ctrl_wr_x),
        .ctrl_wr_y     (ctrl_wr_y),
        .ctrl_wr_en    (ctrl_wr_en),
        .ctrl_wr_data  (ctrl_wr_data),
        .b2d_word_addr (b_word_addr),
        .b2d_rd_en     (b_rd),
        .b2d_rd_grant  (b_rd_grant),
        .b2d_rd_data   (b_rdata)
    );

    task automatic write_pixel(input logic [8:0] x, y, input logic [7:0] col);
        ctrl_wr_x = x; ctrl_wr_y = y; ctrl_wr_data = col; ctrl_wr_en = 1;
        tick(1); ctrl_wr_en = 0;
    endtask

    task automatic read_pixel(input logic [8:0] x, y, output logic [7:0] out);
        a_x = x; a_y = y; a_rd = 1; tick(1); a_rd = 0; tick(1);
        out = a_rdata;
    endtask

    logic [7:0] got;
    int         col_idx;

    initial begin
        $dumpfile("sim/waves/tb_colour_bram.vcd");
        $dumpvars(0, tb_colour_bram);
        a_rd=0; a_we=0; a_x=0; a_y=0; a_wdata=0;
        b_rd=0; b_word_addr=0;
        ctrl_wr_en=0; ctrl_wr_x=0; ctrl_wr_y=0; ctrl_wr_data=0;
        tick(2);

        // ============================================================
        suite("PORT A — basic write then read");
        // ============================================================
        write_pixel(9'd0, 9'd0, 8'h3F);
        read_pixel(9'd0, 9'd0, got);
        check(got == 8'h3F, "pixel (0,0) reads back correct colour");

        write_pixel(9'd15, 9'd0, 8'h2A);
        read_pixel(9'd15, 9'd0, got);
        check(got == 8'h2A, "pixel (15,0) reads back correct colour");

        write_pixel(9'd0, 9'd15, 8'h15);
        read_pixel(9'd0, 9'd15, got);
        check(got == 8'h15, "pixel (0,15) reads back correct — different tile row");

        // ============================================================
        suite("PORT A — tile boundary pixels");
        // ============================================================
        // pixels at tile boundaries to verify tile-ordered addressing
        write_pixel(9'd16, 9'd0,  8'h01); // start of tile (1,0)
        write_pixel(9'd31, 9'd0,  8'h02); // end of tile (1,0) first row
        write_pixel(9'd0,  9'd16, 8'h03); // start of tile (0,1)
        write_pixel(9'd16, 9'd16, 8'h04); // start of tile (1,1)
        tick(1);
        read_pixel(9'd16, 9'd0,  got); check(got == 8'h01, "tile (1,0) first pixel");
        read_pixel(9'd31, 9'd0,  got); check(got == 8'h02, "tile (1,0) last col first row");
        read_pixel(9'd0,  9'd16, got); check(got == 8'h03, "tile (0,1) first pixel");
        read_pixel(9'd16, 9'd16, got); check(got == 8'h04, "tile (1,1) first pixel");

        // ============================================================
        suite("PORT A — overwrite same pixel");
        // ============================================================
        write_pixel(9'd5, 9'd5, 8'h10);
        read_pixel(9'd5, 9'd5, got);
        check(got == 8'h10, "first write");
        write_pixel(9'd5, 9'd5, 8'h3E);
        read_pixel(9'd5, 9'd5, got);
        check(got == 8'h3E, "overwrite succeeds");

        // ============================================================
        suite("PORT A — adjacent pixels in same 64-bit word independent");
        // ============================================================
        // pixels (0,0)..(7,0) share the same 64-bit word (tile 0, word 0)
        for (int i = 0; i < 8; i++) write_pixel(9'(i), 9'd0, 8'(i + 1));
        tick(1);
        for (int i = 0; i < 8; i++) begin
            read_pixel(9'(i), 9'd0, got);
            check(got == 8'(i+1), $sformatf("word-shared pixel (%0d,0) correct", i));
        end

        // ============================================================
        suite("PORT A — write does not corrupt adjacent pixels");
        // ============================================================
        write_pixel(9'd0, 9'd0, 8'hAA);
        write_pixel(9'd1, 9'd0, 8'hBB);
        write_pixel(9'd2, 9'd0, 8'hCC);
        // overwrite middle one
        write_pixel(9'd1, 9'd0, 8'h11);
        tick(1);
        read_pixel(9'd0, 9'd0, got); check(got == 8'hAA, "left neighbour unchanged");
        read_pixel(9'd1, 9'd0, got); check(got == 8'h11, "overwritten pixel correct");
        read_pixel(9'd2, 9'd0, got); check(got == 8'hCC, "right neighbour unchanged");

        // ============================================================
        suite("PORT B — 64-bit read returns 8 correct pixels");
        // ============================================================
        // write 8 known pixels into tile 0, row 0 (word address 0)
        for (int i = 0; i < 8; i++) write_pixel(9'(i), 9'd0, 8'(i + 10));
        tick(2);
        b_word_addr = 13'd0; b_rd = 1; tick(1);
        check(b_rd_grant, "b2d_rd_grant asserted when no controller write");
        b_rd = 0; tick(1);
        for (int i = 0; i < 8; i++)
            check(b_rdata[i*8 +: 8] == 8'(i+10),
                $sformatf("Port B word[%0d] = pixel (%0d,0) correct", i, i));

        // ============================================================
        suite("PORT B — grant denied when controller write in same cycle");
        // ============================================================
        ctrl_wr_en = 1; ctrl_wr_x = 9'd0; ctrl_wr_y = 9'd0; ctrl_wr_data = 8'hFF;
        b_rd = 1; b_word_addr = 13'd0;
        tick(1);
        check(!b_rd_grant, "b2d_rd_grant denied when controller write active");
        ctrl_wr_en = 0; b_rd = 0;

        // ============================================================
        suite("PORT B — grant given next cycle after write clears");
        // ============================================================
        tick(1);
        b_rd = 1; b_word_addr = 13'd0;
        tick(1);
        check(b_rd_grant, "b2d_rd_grant asserted cycle after write clears");
        b_rd = 0; tick(1);

        // ============================================================
        suite("SIMULTANEOUS — read port A and Port B different tiles");
        // ============================================================
        write_pixel(9'd0, 9'd0,   8'h21); // tile 0
        write_pixel(9'd0, 9'd16,  8'h42); // tile (0,1), word addr = 16*32 = 512
        tick(2);
        a_x = 9'd0; a_y = 9'd0; a_rd = 1;
        b_word_addr = 13'd512; b_rd = 1;
        tick(1); a_rd = 0; b_rd = 0; tick(1);
        check(axi_rdata_byte(b_rdata, 0) == 8'h42, "Port B reads tile (0,1) correctly");
        check(a_rdata == 8'h21, "Port A reads tile (0,0) correctly same cycle");

        // ============================================================
        suite("SIMULTANEOUS — write and Port B read to different tiles");
        // ============================================================
        write_pixel(9'd0, 9'd32, 8'hDE); // tile (0,2) = word addr 1024
        b_word_addr = 13'd0; b_rd = 1;   // read tile 0 simultaneously
        tick(1); b_rd = 0;
        // write to tile (0,2), b2d reading tile 0 — no conflict
        check(b_rd_grant, "b2d granted when write targets different tile");

        summary();
        $finish;
    end

    // helper — extract byte 0 from a 64-bit word
    function automatic logic [7:0] axi_rdata_byte(input logic [63:0] w, input int idx);
        return w[idx*8 +: 8];
    endfunction

    initial begin #5000000; $display("[TIMEOUT]"); $finish; end

endmodule

sim/waves/tb_colour_bram.vcd
$date
	Thu May 28 17:03:15 2026
$end
$version
	Icarus Verilog
$end
$timescale
	1ps
$end
$scope module tb_colour_bram $end
$var wire 64 ! b_rdata [63:0] $end
$var wire 1 " b_rd_grant $end
$var wire 8 # a_rdata [7:0] $end
$var reg 1 $ a_rd $end
$var reg 8 % a_wdata [7:0] $end
$var reg 1 & a_we $end
$var reg 9 ' a_x [8:0] $end
$var reg 9 ( a_y [8:0] $end
$var reg 1 ) b_rd $end
$var reg 13 * b_word_addr [12:0] $end
$var reg 1 + clk $end
$var reg 8 , ctrl_wr_data [7:0] $end
$var reg 1 - ctrl_wr_en $end
$var reg 9 . ctrl_wr_x [8:0] $end
$var reg 9 / ctrl_wr_y [8:0] $end
$var reg 8 0 got [7:0] $end
$var integer 32 1 tests_failed [31:0] $end
$var integer 32 2 tests_passed [31:0] $end
$var integer 32 3 tests_run [31:0] $end
$scope function axi_rdata_byte $end
$upscope $end
$scope module dut $end
$var wire 1 ) b2d_rd_en $end
$var wire 1 " b2d_rd_grant $end
$var wire 13 4 b2d_word_addr [12:0] $end
$var wire 1 + clk $end
$var wire 1 $ ctrl_rd_en $end
$var wire 9 5 ctrl_rd_x [8:0] $end
$var wire 9 6 ctrl_rd_y [8:0] $end
$var wire 8 7 ctrl_wr_data [7:0] $end
$var wire 1 - ctrl_wr_en $end
$var wire 9 8 ctrl_wr_x [8:0] $end
$var wire 9 9 ctrl_wr_y [8:0] $end
$var wire 3 : wr_byte_off [2:0] $end
$var reg 3 ; a_byte_off_reg [2:0] $end
$var reg 64 < a_rd_word [63:0] $end
$var reg 64 = b2d_rd_data [63:0] $end
$var reg 64 > b_wr_word [63:0] $end
$var reg 8 ? ctrl_rd_data [7:0] $end
$scope function byte_off $end
$var reg 16 @ ta [15:0] $end
$var reg 9 A x [8:0] $end
$var reg 9 B y [8:0] $end
$upscope $end
$scope function word_addr $end
$var reg 16 C ta [15:0] $end
$var reg 9 D x [8:0] $end
$var reg 9 E y [8:0] $end
$upscope $end
$upscope $end
$scope begin $ivl_for_loop6 $end
$var integer 32 F i [31:0] $end
$upscope $end
$scope begin $ivl_for_loop7 $end
$var integer 32 G i [31:0] $end
$upscope $end
$scope begin $ivl_for_loop8 $end
$var integer 32 H i [31:0] $end
$upscope $end
$scope begin $ivl_for_loop9 $end
$var integer 32 I i [31:0] $end
$upscope $end
$scope task check $end
$upscope $end
$scope task read_pixel $end
$upscope $end
$scope task suite $end
$upscope $end
$scope task summary $end
$upscope $end
$scope task tick $end
$upscope $end
$scope task write_pixel $end
$upscope $end
$upscope $end
$enddefinitions $end
$comment Show the parameter values. $end
$dumpall
$end
#0
$dumpvars
b0 I
b0 H
b0 G
b0 F
b0 E
b0 D
b0 C
b0 B
b0 A
b0 @
bx ?
bx00000000 >
bx =
bx <
bx ;
b0 :
b0 9
b0 8
b0 7
b0 6
b0 5
b0 4
b0 3
b0 2
b0 1
bx 0
b0 /
b0 .
0-
b0 ,
0+
b0 *
0)
b0 (
b0 '
0&
b0 %
0$
bx #
0"
bx !
$end
#5000
1+
#10000
0+
#15000
1+
#16000
bx00111111 >
1-
b111111 ,
b111111 7
#20000
0+
#25000
1+
#26000
1$
0-
#30000
0+
#35000
b111111 #
b111111 ?
b0 ;
bx00111111 <
1+
#36000
0$
#40000
0+
#45000
1+
#46000
b101010xxxxxxxxxxxxxxxxxxxxxxxxxxxxxxxxxxxxxxxxxxxxxxxxxxxxxxxx >
b1111 C
b1111 D
b111 :
b1111 @
b1111 A
1-
b101010 ,
b101010 7
b1111 .
b1111 8
b1 2
b1 3
b111111 0
#50000
0+
#55000
1+
#56000
1$
b1111 '
b1111 5
0-
#60000
0+
#65000
b101010 #
b101010 ?
b111 ;
b101010xxxxxxxxxxxxxxxxxxxxxxxxxxxxxxxxxxxxxxxxxxxxxxxxxxxxxxxx <
1+
#66000
0$
#70000
0+
#75000
1+
#76000
bx00010101 >
b11110000 C
b0 D
b1111 E
b0 :
b11110000 @
b1111 B
b0 A
1-
b10101 ,
b10101 7
b1111 /
b1111 9
b0 .
b0 8
b10 2
b10 3
b101010 0
#80000
0+
#85000
1+
#86000
1$
b1111 (
b1111 6
b0 '
b0 5
0-
#90000
0+
#95000
b10101 #
b10101 ?
b0 ;
bx00010101 <
1+
#96000
0$
#100000
0+
#105000
1+
#106000
bx00000001 >
b100000000 C
b10000 D
b0 E
b100000000 @
b0 B
b10000 A
1-
b1 ,
b1 7
b0 /
b0 9
b10000 .
b10000 8
b11 2
b11 3
b10101 0
#110000
0+
#115000
1+
#116000
b10xxxxxxxxxxxxxxxxxxxxxxxxxxxxxxxxxxxxxxxxxxxxxxxxxxxxxxxx >
b100001111 C
b11111 D
b111 :
b100001111 @
b11111 A
b10 ,
b10 7
b11111 .
b11111 8
1-
#120000
0+
#125000
1+
#126000
bx00000011 >
b1000000000000 C
b0 D
b10000 E
b0 :
b1000000000000 @
b10000 B
b0 A
b11 ,
b11 7
b10000 /
b10000 9
b0 .
b0 8
1-
#130000
0+
#135000
1+
#136000
bx00000100 >
b1000100000000 C
b10000 D
b1000100000000 @
b10000 A
b100 ,
b100 7
b10000 .
b10000 8
1-
#140000
0+
#145000
1+
#146000
0-
#150000
0+
#155000
1+
#156000
1$
b0 (
b0 6
b10000 '
b10000 5
#160000
0+
#165000
b1 #
b1 ?
bx00000001 <
b100000000 @
b0 B
b1000100000000 C
b10000 E
1+
#166000
0$
#170000
0+
#175000
1+
#176000
1$
b11111 '
b11111 5
b100 2
b100 3
b1 0
#180000
0+
#185000
b10 #
b10 ?
b111 ;
b10xxxxxxxxxxxxxxxxxxxxxxxxxxxxxxxxxxxxxxxxxxxxxxxxxxxxxxxx <
b100001111 @
b11111 A
b1000100000000 C
b10000 D
b10000 E
1+
#186000
0$
#190000
0+
#195000
1+
#196000
1$
b10000 (
b10000 6
b0 '
b0 5
b101 2
b101 3
b10 0
#200000
0+
#205000
b11 #
b11 ?
b0 ;
bx00000011 <
b1000000000000 @
b0 A
b10000 B
b1000100000000 C
b10000 D
1+
#206000
0$
#210000
0+
#215000
1+
#216000
1$
b10000 '
b10000 5
b110 2
b110 3
b11 0
#220000
0+
#225000
b100 #
b100 ?
bx00000100 <
b1000100000000 @
b10000 A
1+
#226000
0$
#230000
0+
#235000
1+
#236000
bx00010000xxxxxxxxxxxxxxxxxxxxxxxxxxxxxxxxxxxxxxxx >
b1010101 C
b101 D
b101 E
b101 :
b1010101 @
b101 B
b101 A
1-
b10000 ,
b10000 7
b101 /
b101 9
b101 .
b101 8
b111 2
b111 3
b100 0
#240000
0+
#245000
1+
#246000
1$
b101 (
b101 6
b101 '
b101 5
0-
#250000
0+
#255000
b10000 #
b10000 ?
b101 ;
bx00010000xxxxxxxxxxxxxxxxxxxxxxxxxxxxxxxxxxxxxxxx <
1+
#256000
0$
#260000
0+
#265000
1+
#266000
bx00111110xxxxxxxxxxxxxxxxxxxxxxxxxxxxxxxxxxxxxxxx >
1-
b111110 ,
b111110 7
b1000 2
b1000 3
b10000 0
#270000
0+
#275000
1+
#276000
1$
0-
#280000
0+
#285000
b111110 #
b111110 ?
bx00111110xxxxxxxxxxxxxxxxxxxxxxxxxxxxxxxxxxxxxxxx <
1+
#286000
0$
#290000
0+
#295000
1+
#296000
bx00000001 >
b0 C
b0 D
b0 E
b0 :
b0 @
b0 B
b0 A
1-
b1 ,
b1 7
b0 /
b0 9
b0 .
b0 8
b1001 2
b1001 3
b111110 0
#300000
0+
#305000
1+
#306000
bx0000001000000001 >
b1 C
b1 D
b1 :
b1 @
b1 A
b10 ,
b10 7
b1 .
b1 8
b1 F
1-
#310000
0+
#315000
1+
#316000
bx000000110000001000000001 >
b10 C
b10 D
b10 :
b10 @
b10 A
b11 ,
b11 7
b10 .
b10 8
b10 F
1-
#320000
0+
#325000
1+
#326000
bx00000100000000110000001000000001 >
b11 C
b11 D
b11 :
b11 @
b11 A
b100 ,
b100 7
b11 .
b11 8
b11 F
1-
#330000
0+
#335000
1+
#336000
bx0000010100000100000000110000001000000001 >
b100 C
b100 D
b100 :
b100 @
b100 A
b101 ,
b101 7
b100 .
b100 8
b100 F
1-
#340000
0+
#345000
1+
#346000
bx000001100000010100000100000000110000001000000001 >
b101 C
b101 D
b101 :
b101 @
b101 A
b110 ,
b110 7
b101 .
b101 8
b101 F
1-
#350000
0+
#355000
1+
#356000
bx00000111000001100000010100000100000000110000001000000001 >
b110 C
b110 D
b110 :
b110 @
b110 A
b111 ,
b111 7
b110 .
b110 8
b110 F
1-
#360000
0+
#365000
1+
#366000
b100000000111000001100000010100000100000000110000001000000001 >
b111 C
b111 D
b111 :
b111 @
b111 A
b1000 ,
b1000 7
b111 .
b111 8
b111 F
1-
#370000
0+
#375000
1+
#376000
b1000 F
0-
#380000
0+
#385000
1+
#386000
1$
b0 (
b0 6
b0 '
b0 5
#390000
0+
#395000
b1 #
b1 ?
b0 ;
b100000000111000001100000010100000100000000110000001000000001 <
b0 @
b0 A
b111 C
b111 D
1+
#396000
0$
#400000
0+
#405000
1+
#406000
1$
b1 '
b1 5
b1 G
b1010 2
b1010 3
b1 0
#410000
0+
#415000
b10 #
b10 ?
b1 ;
b1 @
b1 A
b111 C
b111 D
1+
#416000
0$
#420000
0+
#425000
1+
#426000
1$
b10 '
b10 5
b10 G
b1011 2
b1011 3
b10 0
#430000
0+
#435000
b11 #
b11 ?
b10 ;
b10 @
b10 A
b111 C
b111 D
1+
#436000
0$
#440000
0+
#445000
1+
#446000
1$
b11 '
b11 5
b11 G
b1100 2
b1100 3
b11 0
#450000
0+
#455000
b100 #
b100 ?
b11 ;
b11 @
b11 A
b111 C
b111 D
1+
#456000
0$
#460000
0+
#465000
1+
#466000
1$
b100 '
b100 5
b100 G
b1101 2
b1101 3
b100 0
#470000
0+
#475000
b101 #
b101 ?
b100 ;
b100 @
b100 A
b111 C
b111 D
1+
#476000
0$
#480000
0+
#485000
1+
#486000
1$
b101 '
b101 5
b101 G
b1110 2
b1110 3
b101 0
#490000
0+
#495000
b110 #
b110 ?
b101 ;
b101 @
b101 A
b111 C
b111 D
1+
#496000
0$
#500000
0+
#505000
1+
#506000
1$
b110 '
b110 5
b110 G
b1111 2
b1111 3
b110 0
#510000
0+
#515000
b111 #
b111 ?
b110 ;
b110 @
b110 A
b111 C
b111 D
1+
#516000
0$
#520000
0+
#525000
1+
#526000
1$
b111 '
b111 5
b111 G
b10000 2
b10000 3
b111 0
#530000
0+
#535000
b1000 #
b1000 ?
b111 ;
b111 @
b111 A
1+
#536000
0$
#540000
0+
#545000
1+
#546000
b100000000111000001100000010100000100000000110000001010101010 >
b0 C
b0 D
b0 :
b0 @
b0 A
1-
b10101010 ,
b10101010 7
b0 .
b0 8
b1000 G
b10001 2
b10001 3
b1000 0
#550000
0+
#555000
1+
#556000
b100000000111000001100000010100000100000000111011101110101010 >
b1 C
b1 D
b1 :
b1 @
b1 A
b10111011 ,
b10111011 7
b1 .
b1 8
1-
#560000
0+
#565000
1+
#566000
b100000000111000001100000010100000100110011001011101110101010 >
b10 C
b10 D
b10 :
b10 @
b10 A
b11001100 ,
b11001100 7
b10 .
b10 8
1-
#570000
0+
#575000
1+
#576000
b100000000111000001100000010100000100110011000001000110101010 >
b1 C
b1 D
b1 :
b1 @
b1 A
b10001 ,
b10001 7
b1 .
b1 8
1-
#580000
0+
#585000
1+
#586000
0-
#590000
0+
#595000
1+
#596000
1$
b0 '
b0 5
#600000
0+
#605000
b10101010 #
b10101010 ?
b0 ;
b100000000111000001100000010100000100110011000001000110101010 <
b0 @
b0 A
b1 C
b1 D
1+
#606000
0$
#610000
0+
#615000
1+
#616000
1$
b1 '
b1 5
b10010 2
b10010 3
b10101010 0
#620000
0+
#625000
b10001 #
b10001 ?
b1 ;
b1 @
b1 A
1+
#626000
0$
#630000
0+
#635000
1+
#636000
1$
b10 '
b10 5
b10011 2
b10011 3
b10001 0
#640000
0+
#645000
b11001100 #
b11001100 ?
b10 ;
b10 @
b10 A
b1 C
b1 D
1+
#646000
0$
#650000
0+
#655000
1+
#656000
b100000000111000001100000010100000100110011000001000100001010 >
b0 C
b0 D
b0 :
b0 @
b0 A
1-
b1010 ,
b1010 7
b0 .
b0 8
b10100 2
b10100 3
b11001100 0
#660000
0+
#665000
1+
#666000
b100000000111000001100000010100000100110011000000101100001010 >
b1 C
b1 D
b1 :
b1 @
b1 A
b1011 ,
b1011 7
b1 .
b1 8
b1 H
1-
#670000
0+
#675000
1+
#676000
b100000000111000001100000010100000100000011000000101100001010 >
b10 C
b10 D
b10 :
b10 @
b10 A
b1100 ,
b1100 7
b10 .
b10 8
b10 H
1-
#680000
0+
#685000
1+
#686000
b100000000111000001100000010100001101000011000000101100001010 >
b11 C
b11 D
b11 :
b11 @
b11 A
b1101 ,
b1101 7
b11 .
b11 8
b11 H
1-
#690000
0+
#695000
1+
#696000
b100000000111000001100000111000001101000011000000101100001010 >
b100 C
b100 D
b100 :
b100 @
b100 A
b1110 ,
b1110 7
b100 .
b100 8
b100 H
1-
#700000
0+
#705000
1+
#706000
b100000000111000011110000111000001101000011000000101100001010 >
b101 C
b101 D
b101 :
b101 @
b101 A
b1111 ,
b1111 7
b101 .
b101 8
b101 H
1-
#710000
0+
#715000
1+
#716000
b100000010000000011110000111000001101000011000000101100001010 >
b110 C
b110 D
b110 :
b110 @
b110 A
b10000 ,
b10000 7
b110 .
b110 8
b110 H
1-
#720000
0+
#725000
1+
#726000
b1000100010000000011110000111000001101000011000000101100001010 >
b111 C
b111 D
b111 :
b111 @
b111 A
b10001 ,
b10001 7
b111 .
b111 8
b111 H
1-
#730000
0+
#735000
1+
#736000
b1000 H
0-
#740000
0+
#745000
1+
#750000
0+
#755000
1+
#756000
1"
1)
#760000
0+
#765000
b1000100010000000011110000111000001101000011000000101100001010 !
b1000100010000000011110000111000001101000011000000101100001010 =
1+
#766000
0"
0)
b10101 2
b10101 3
#770000
0+
#775000
1+
#776000
b1000100010000000011110000111000001101000011000000101111111111 >
b0 C
b0 D
b0 :
b0 @
b0 A
1)
b11111111 ,
b11111111 7
b0 .
b0 8
1-
b1000 I
b11101 2
b11101 3
#780000
0+
#785000
1+
#786000
0)
0-
b11110 2
b11110 3
#790000
0+
#795000
1+
#796000
1"
1)
#800000
0+
#805000
b1000100010000000011110000111000001101000011000000101111111111 !
b1000100010000000011110000111000001101000011000000101111111111 =
1+
#806000
0"
0)
b11111 2
b11111 3
#810000
0+
#815000
1+
#816000
b1000100010000000011110000111000001101000011000000101100100001 >
1-
b100001 ,
b100001 7
#820000
0+
#825000
1+
#826000
bx01000010 >
b1000000000000 C
b10000 E
b1000000000000 @
b10000 B
b1000010 ,
b1000010 7
b10000 /
b10000 9
1-
#830000
0+
#835000
1+
#836000
0-
#840000
0+
#845000
1+
#850000
0+
#855000
1+
#856000
1"
1)
b1000000000 *
b1000000000 4
1$
b0 '
b0 5
#860000
0+
#865000
b100001 #
b100001 ?
b0 ;
b1000100010000000011110000111000001101000011000000101100100001 <
bx01000010 !
bx01000010 =
b0 @
b0 B
b1000000000000 C
b10000 E
1+
#866000
0"
0)
0$
#870000
0+
#875000
1+
#876000
bx11011110 >
b10000000000000 C
b100000 E
b10000000000000 @
b100000 B
1-
b11011110 ,
b11011110 7
b100000 /
b100000 9
b100001 2
b100001 3
#880000
0+
#885000
1+
#886000
1"
1)
b0 *
b0 4
0-
#890000
0+
#895000
b1000100010000000011110000111000001101000011000000101100100001 !
b1000100010000000011110000111000001101000011000000101100100001 =
1+
#896000
0"
b100010 2
b100010 3
0)
