hdl/memory/state_bram.sv
// Packed 2-bit state storage for one 256x256 sixteenth.
// 4 pixels per byte, tile-ordered addressing.
// State: 00=uncomputed, 01=in-progress, 11=done, 10=unused

module state_bram (
    input  logic        clk,
    input  logic        rst,

    input  logic [8:0]  a_x,
    input  logic [8:0]  a_y,
    input  logic        a_rd,
    input  logic        a_we,
    input  logic [1:0]  a_wstate,
    output logic [1:0]  a_rstate
);

    (* ram_style = "block" *)
    logic [7:0] mem [0:16383];

    logic [15:0] tile_addr;
    logic [13:0] byte_addr;
    logic [1:0]  bit_slot;

    assign tile_addr = {a_y[7:4], a_x[7:4], a_y[3:0], a_x[3:0]};
    assign byte_addr = tile_addr[15:2];
    assign bit_slot  = tile_addr[1:0];

    // Registered read
    logic [7:0] rd_byte;
    logic       post_rst;

    always_ff @(posedge clk) begin
        if (rst)
            post_rst <= 1'b1;
        else if (a_rd)
            post_rst <= 1'b0;
        if (a_rd)
            rd_byte <= mem[byte_addr];
    end

    logic [7:0] rd_byte_out;
    assign rd_byte_out = post_rst ? 8'h00 : rd_byte;

    always_comb begin
        case (bit_slot)
            2'b00: a_rstate = rd_byte_out[1:0];
            2'b01: a_rstate = rd_byte_out[3:2];
            2'b10: a_rstate = rd_byte_out[5:4];
            default: a_rstate = rd_byte_out[7:6];
        endcase
    end

    // Read-modify-write
    logic [7:0] cur_byte, new_byte;
    assign cur_byte = mem[byte_addr];

    always_comb begin
        new_byte = cur_byte;
        case (bit_slot)
            2'b00: new_byte[1:0] = a_wstate;
            2'b01: new_byte[3:2] = a_wstate;
            2'b10: new_byte[5:4] = a_wstate;
            default: new_byte[7:6] = a_wstate;
        endcase
    end

    initial begin
        for (int i = 0; i < 16384; i++)
            mem[i] = 8'h00;
    end

    always_ff @(posedge clk) begin
        if (a_we && !rst)
            mem[byte_addr] <= new_byte;
    end

endmodule

tb/memory/tb_state_bram.sv
`timescale 1ns/1ps

module tb_state_bram;

    int tests_run = 0, tests_passed = 0, tests_failed = 0;
    string current_suite = "";

    task automatic suite(input string name);
        current_suite = name;
        $display("\n%0s", {72{"="}});
        $display("  SUITE: %s", name);
        $display("%0s", {72{"="}});
    endtask

    task automatic check(input logic cond, input string desc);
        tests_run++;
        if (cond) begin tests_passed++; $display("  [PASS] %s", desc); end
        else       begin tests_failed++; $display("  [FAIL] %s  (suite: %s)", desc, current_suite); end
    endtask

    task automatic summary();
        $display("\n%0s", {72{"="}});
        $display("  RESULTS: %0d / %0d passed", tests_passed, tests_run);
        if (tests_failed == 0) $display("  ALL TESTS PASSED");
        else $display("  %0d TEST(S) FAILED", tests_failed);
        $display("%0s\n", {72{"="}});
    endtask

    logic       clk = 0;
    always #5 clk = ~clk;
    task automatic tick(input int n = 1); repeat(n) @(posedge clk); #1; endtask

    logic [8:0] a_x, a_y;
    logic       a_rd, a_we;
    logic [1:0] a_wstate, a_rstate;
    logic       rst;

    state_bram dut (
        .clk     (clk),
        .rst     (rst),
        .a_x     (a_x),
        .a_y     (a_y),
        .a_rd    (a_rd),
        .a_we    (a_we),
        .a_wstate(a_wstate),
        .a_rstate(a_rstate)
    );

    task automatic write_state(input logic [8:0] x, y, input logic [1:0] s);
        a_x = x; a_y = y; a_wstate = s; a_we = 1; tick(1); a_we = 0;
    endtask

    task automatic read_state(input logic [8:0] x, y, output logic [1:0] out);
        a_x = x; a_y = y; a_rd = 1; tick(1); a_rd = 0; tick(1);
        out = a_rstate;
    endtask

    logic [1:0] got;

    initial begin
        $dumpfile("sim/waves/tb_state_bram.vcd");
        $dumpvars(0, tb_state_bram);
        rst=0; a_rd=0; a_we=0; a_x=0; a_y=0; a_wstate=0;
        tick(2);

        suite("WRITE + READ  basic state transitions");
        write_state(9'd0, 9'd0, 2'b01);
        read_state(9'd0, 9'd0, got);
        check(got == 2'b01, "pixel (0,0) state=01 reads back");

        write_state(9'd0, 9'd0, 2'b11);
        read_state(9'd0, 9'd0, got);
        check(got == 2'b11, "pixel (0,0) state=11 after update");

        suite("PACKING  4 pixels per byte independent");
        // pixels (0,0),(1,0),(2,0),(3,0) share the same packed byte
        write_state(9'd0, 9'd0, 2'b01);
        write_state(9'd1, 9'd0, 2'b11);
        write_state(9'd2, 9'd0, 2'b01);
        write_state(9'd3, 9'd0, 2'b00);
        tick(1);
        read_state(9'd0, 9'd0, got); check(got == 2'b01, "packed px0 = 01");
        read_state(9'd1, 9'd0, got); check(got == 2'b11, "packed px1 = 11");
        read_state(9'd2, 9'd0, got); check(got == 2'b01, "packed px2 = 01");
        read_state(9'd3, 9'd0, got); check(got == 2'b00, "packed px3 = 00");

        suite("PACKING  write one slot does not corrupt others");
        write_state(9'd0, 9'd0, 2'b11);
        write_state(9'd1, 9'd0, 2'b11);
        write_state(9'd2, 9'd0, 2'b11);
        write_state(9'd3, 9'd0, 2'b11);
        write_state(9'd1, 9'd0, 2'b01); // overwrite only slot 1
        tick(1);
        read_state(9'd0, 9'd0, got); check(got == 2'b11, "slot 0 unchanged");
        read_state(9'd1, 9'd0, got); check(got == 2'b01, "slot 1 updated");
        read_state(9'd2, 9'd0, got); check(got == 2'b11, "slot 2 unchanged");
        read_state(9'd3, 9'd0, got); check(got == 2'b11, "slot 3 unchanged");

        suite("TILE BOUNDARY  pixels at tile edges");
        write_state(9'd15, 9'd0,  2'b11); // last pixel of tile 0 first row
        write_state(9'd16, 9'd0,  2'b01); // first pixel of tile 1 first row
        write_state(9'd0,  9'd16, 2'b11); // first pixel of tile in row 1
        tick(1);
        read_state(9'd15, 9'd0,  got); check(got == 2'b11, "last px tile 0 row 0");
        read_state(9'd16, 9'd0,  got); check(got == 2'b01, "first px tile 1 row 0");
        read_state(9'd0,  9'd16, got); check(got == 2'b11, "first px tile row 1");

        suite("CORNERS  extreme pixel coordinates");
        write_state(9'd255, 9'd255, 2'b11);
        read_state(9'd255, 9'd255, got);
        check(got == 2'b11, "pixel (255,255)  bottom right corner");

        write_state(9'd255, 9'd0, 2'b01);
        read_state(9'd255, 9'd0, got);
        check(got == 2'b01, "pixel (255,0)  top right corner");

        write_state(9'd0, 9'd255, 2'b11);
        read_state(9'd0, 9'd255, got);
        check(got == 2'b11, "pixel (0,255)  bottom left corner");

        suite("RESET  writes blocked during rst, existing values preserved");
        // rst does not clear BRAM memory (hardware limitation).
        // Verify: writes are blocked while rst high, old value preserved after rst.
        write_state(9'd10, 9'd10, 2'b11);
        rst = 1;
        // attempt write during rst  should be blocked
        write_state(9'd10, 9'd10, 2'b01);
        rst = 0; tick(1);
        // read back  should still be 11 since write was blocked
        read_state(9'd10, 9'd10, got);
        check(got == 2'b11, "write blocked during rst  value preserved as 11");

        suite("STATE MACHINE  00 -> 01 -> 11 sequence");
        rst = 1; tick(1); rst = 0; tick(1);
        read_state(9'd5, 9'd5, got); check(got == 2'b00, "initial state 00");
        write_state(9'd5, 9'd5, 2'b01);
        read_state(9'd5, 9'd5, got); check(got == 2'b01, "transitions to 01 on queue");
        write_state(9'd5, 9'd5, 2'b11);
        read_state(9'd5, 9'd5, got); check(got == 2'b11, "transitions to 11 on done");

        summary();
        $finish;
    end

    initial begin #2000000; $display("[TIMEOUT]"); $finish; end

endmodule

sim/waves/tb_state_bram.vcd
$date
	Fri May 29 15:16:06 2026
$end
$version
	Icarus Verilog
$end
$timescale
	1ps
$end
$scope module tb_state_bram $end
$var wire 2 ! a_rstate [1:0] $end
$var reg 1 " a_rd $end
$var reg 1 # a_we $end
$var reg 2 $ a_wstate [1:0] $end
$var reg 9 % a_x [8:0] $end
$var reg 9 & a_y [8:0] $end
$var reg 1 ' clk $end
$var reg 2 ( got [1:0] $end
$var reg 1 ) rst $end
$var integer 32 * tests_failed [31:0] $end
$var integer 32 + tests_passed [31:0] $end
$var integer 32 , tests_run [31:0] $end
$scope module dut $end
$var wire 1 " a_rd $end
$var wire 1 # a_we $end
$var wire 2 - a_wstate [1:0] $end
$var wire 9 . a_x [8:0] $end
$var wire 9 / a_y [8:0] $end
$var wire 1 ' clk $end
$var wire 8 0 cur_byte [7:0] $end
$var wire 1 ) rst $end
$var wire 16 1 tile_addr [15:0] $end
$var wire 8 2 rd_byte_out [7:0] $end
$var wire 14 3 byte_addr [13:0] $end
$var wire 2 4 bit_slot [1:0] $end
$var reg 2 5 a_rstate [1:0] $end
$var reg 8 6 new_byte [7:0] $end
$var reg 1 7 post_rst $end
$var reg 8 8 rd_byte [7:0] $end
$scope begin $ivl_for_loop2 $end
$var integer 32 9 i [31:0] $end
$upscope $end
$upscope $end
$scope task check $end
$upscope $end
$scope task read_state $end
$upscope $end
$scope task suite $end
$upscope $end
$scope task summary $end
$upscope $end
$scope task tick $end
$upscope $end
$scope task write_state $end
$upscope $end
$upscope $end
$enddefinitions $end
$comment Show the parameter values. $end
$dumpall
$end
#0
$dumpvars
b100000000000000 9
bx 8
x7
b0 6
bx 5
b0 4
b0 3
bx 2
b0 1
b0 0
b0 /
b0 .
b0 -
b0 ,
b0 +
b0 *
0)
bx (
0'
b0 &
b0 %
b0 $
0#
0"
bx !
$end
#5000
1'
#10000
0'
#15000
1'
#16000
b1 6
1#
b1 $
b1 -
#20000
0'
#25000
b1 0
1'
#26000
1"
0#
#30000
0'
#35000
b1 !
b1 5
b1 2
b1 8
07
1'
#36000
0"
#40000
0'
#45000
1'
#46000
b11 6
1#
b11 $
b11 -
b1 +
b1 ,
b1 (
#50000
0'
#55000
b11 0
1'
#56000
1"
0#
#60000
0'
#65000
b11 !
b11 5
b11 2
b11 8
1'
#66000
0"
#70000
0'
#75000
1'
#76000
b1 6
1#
b1 $
b1 -
b10 +
b10 ,
b11 (
#80000
0'
#85000
b1 0
1'
#86000
b0 !
b0 5
b1 4
b1101 6
b1 1
b11 $
b11 -
b1 %
b1 .
1#
#90000
0'
#95000
b1101 0
1'
#96000
b10 4
b11101 6
b10 1
b1 $
b1 -
b10 %
b10 .
1#
#100000
0'
#105000
b11101 0
1'
#106000
b11 4
b11101 6
b11 1
b0 $
b0 -
b11 %
b11 .
1#
#110000
0'
#115000
1'
#116000
0#
#120000
0'
#125000
1'
#126000
b11100 6
b11 !
b11 5
b0 4
b0 1
1"
b0 %
b0 .
#130000
0'
#135000
b1 !
b1 5
b11101 2
b11101 8
1'
#136000
0"
#140000
0'
#145000
1'
#146000
b10001 6
b11 !
b11 5
b1 4
b1 1
1"
b1 %
b1 .
b11 +
b11 ,
b1 (
#150000
0'
#155000
1'
#156000
0"
#160000
0'
#165000
1'
#166000
b1101 6
b1 !
b1 5
b10 4
b10 1
1"
b10 %
b10 .
b100 +
b100 ,
b11 (
#170000
0'
#175000
1'
#176000
0"
#180000
0'
#185000
1'
#186000
b11101 6
b0 !
b0 5
b11 4
b11 1
1"
b11 %
b11 .
b101 +
b101 ,
b1 (
#190000
0'
#195000
1'
#196000
0"
#200000
0'
#205000
1'
#206000
b1 !
b1 5
b0 4
b11111 6
b0 1
1#
b11 $
b11 -
b0 %
b0 .
b110 +
b110 ,
b0 (
#210000
0'
#215000
b11111 0
1'
#216000
b11 !
b11 5
b1 4
b1 1
b1 %
b1 .
1#
#220000
0'
#225000
1'
#226000
b111111 6
b1 !
b1 5
b10 4
b10 1
b10 %
b10 .
1#
#230000
0'
#235000
b111111 0
1'
#236000
b11111111 6
b0 !
b0 5
b11 4
b11 1
b11 %
b11 .
1#
#240000
0'
#245000
b11111111 0
1'
#246000
b11 !
b11 5
b1 4
b11110111 6
b1 1
b1 $
b1 -
b1 %
b1 .
1#
#250000
0'
#255000
b11110111 0
1'
#256000
0#
#260000
0'
#265000
1'
#266000
b11110101 6
b1 !
b1 5
b0 4
b0 1
1"
b0 %
b0 .
#270000
0'
#275000
b11 !
b11 5
b11110111 2
b11110111 8
1'
#276000
0"
#280000
0'
#285000
1'
#286000
b11110111 6
b1 !
b1 5
b1 4
b1 1
1"
b1 %
b1 .
b111 +
b111 ,
b11 (
#290000
0'
#295000
1'
#296000
0"
#300000
0'
#305000
1'
#306000
b11010111 6
b11 !
b11 5
b10 4
b10 1
1"
b10 %
b10 .
b1000 +
b1000 ,
b1 (
#310000
0'
#315000
1'
#316000
0"
#320000
0'
#325000
1'
#326000
b1110111 6
b11 4
b11 1
1"
b11 %
b11 .
b1001 +
b1001 ,
b11 (
#330000
0'
#335000
1'
#336000
0"
#340000
0'
#345000
1'
#346000
b0 0
b11 3
b11000000 6
b1111 1
1#
b11 $
b11 -
b1111 %
b1111 .
b1010 +
b1010 ,
#350000
0'
#355000
b11000000 0
1'
#356000
b0 0
b1000000 3
b0 4
b1 6
b100000000 1
b1 $
b1 -
b10000 %
b10000 .
1#
#360000
0'
#365000
b1 0
1'
#366000
b0 0
b10000000000 3
b11 6
b1000000000000 1
b11 $
b11 -
b10000 &
b10000 /
b0 %
b0 .
1#
#370000
0'
#375000
b11 0
1'
#376000
0#
#380000
0'
#385000
1'
#386000
b11000000 6
b11000000 0
b11 3
b11 4
b1111 1
1"
b0 &
b0 /
b1111 %
b1111 .
#390000
0'
#395000
b11000000 2
b11000000 8
1'
#396000
0"
#400000
0'
#405000
1'
#406000
b11 6
b0 !
b0 5
b1 0
b1000000 3
b0 4
b100000000 1
1"
b10000 %
b10000 .
b1011 +
b1011 ,
#410000
0'
#415000
b1 !
b1 5
b1 2
b1 8
1'
#416000
0"
#420000
0'
#425000
1'
#426000
b11 0
b10000000000 3
b1000000000000 1
1"
b10000 &
b10000 /
b0 %
b0 .
b1100 +
b1100 ,
b1 (
#430000
0'
#435000
b11 !
b11 5
b11 2
b11 8
1'
#436000
0"
#440000
0'
#445000
1'
#446000
b11000000 6
b0 !
b0 5
b0 0
b11111111111111 3
b11 4
b1111111111111111 1
1#
b11111111 &
b11111111 /
b11111111 %
b11111111 .
b1101 +
b1101 ,
b11 (
#450000
0'
#455000
b11000000 0
1'
#456000
1"
0#
#460000
0'
#465000
b11 !
b11 5
b11000000 2
b11000000 8
1'
#466000
0"
#470000
0'
#475000
1'
#476000
b0 0
b1111000011 3
b1000000 6
b111100001111 1
1#
b1 $
b1 -
b0 &
b0 /
b1110 +
b1110 ,
#480000
0'
#485000
b1000000 0
1'
#486000
1"
0#
#490000
0'
#495000
b1 !
b1 5
b1000000 2
b1000000 8
1'
#496000
0"
#500000
0'
#505000
1'
#506000
b0 !
b0 5
b0 0
b11110000111100 3
b0 4
b11 6
b1111000011110000 1
1#
b11 $
b11 -
b11111111 &
b11111111 /
b0 %
b0 .
b1111 +
b1111 ,
b1 (
#510000
0'
#515000
b11 0
1'
#516000
1"
0#
#520000
0'
#525000
b11 !
b11 5
b11 2
b11 8
1'
#526000
0"
#530000
0'
#535000
1'
#536000
b110000 6
b0 !
b0 5
b0 0
b101010 3
b10 4
b10101010 1
1#
b1010 &
b1010 /
b1010 %
b1010 .
b10000 +
b10000 ,
b11 (
#540000
0'
#545000
b110000 0
1'
#546000
b10000 6
b1 $
b1 -
1)
1#
#550000
0'
#555000
b0 2
17
1'
#556000
0)
0#
#560000
0'
#565000
1'
#566000
1"
#570000
0'
#575000
b11 !
b11 5
b110000 2
b110000 8
07
1'
#576000
0"
#580000
0'
#585000
1'
#586000
1)
b10001 +
b10001 ,
#590000
0'
#595000
b0 !
b0 5
b0 2
17
1'
#596000
0)
#600000
0'
#605000
1'
#606000
b100 6
b0 0
b10101 3
b1 4
b1010101 1
1"
b101 &
b101 /
b101 %
b101 .
#610000
0'
#615000
b0 8
07
1'
#616000
0"
#620000
0'
#625000
1'
#626000
1#
b10010 +
b10010 ,
b0 (
#630000
0'
#635000
b100 0
1'
#636000
1"
0#
#640000
0'
#645000
b1 !
b1 5
b100 2
b100 8
1'
#646000
0"
#650000
0'
#655000
1'
#656000
b1100 6
1#
b11 $
b11 -
b10011 +
b10011 ,
b1 (
#660000
0'
#665000
b1100 0
1'
#666000
1"
0#
#670000
0'
#675000
b11 !
b11 5
b1100 2
b1100 8
1'
#676000
0"
#680000
0'
#685000
1'
#686000
b10100 +
b10100 ,
b11 (
